{
  "scraping_date": "2025-09-27T14:29:43.854516",
  "portal_url": "https://portal.nabh.co/frmViewAccreditedEntryLevelHosp.aspx",
  "scraping_method": "Direct table extraction",
  "total_hospitals": 3029,
  "by_state": {
    "Tamil Nadu": 398,
    "Maharashtra": 383,
    "Uttar Pradesh": 361,
    "Karnataka": 236,
    "Madhya Pradesh": 223,
    "Kerala": 188,
    "Andhra Pradesh": 188,
    "West Bengal": 184,
    "Telangana": 148,
    "Rajasthan": 124,
    "Gujarat": 117,
    "Haryana": 80,
    "Chattisgarh": 70,
    "Delhi": 56,
    "Uttarakhand": 46,
    "Bihar": 45,
    "Punjab": 37,
    "Jharkhand": 35,
    "Assam": 34,
    "Orissa": 16,
    "Odisha": 16,
    "Pondicherry": 8,
    "Chhattisgarh": 7,
    "Meghalaya": 5,
    "Bangalore": 5,
    "Goa": 4,
    "Nagaland": 3,
    "Jammu And Kashmir": 3,
    "Mizoram": 3,
    "Puducherry": 3,
    "Manipur": 1,
    "Tripura": 1,
    "Sikkim": 1
  },
  "by_city": {
    "Bangalore": 99,
    "Bhopal": 86,
    "Hyderabad": 76,
    "Pune": 73,
    "Chennai": 65,
    "Kolkata": 62,
    "Lucknow": 55,
    "Mumbai": 47,
    "Coimbatore": 43,
    "Guntur": 42,
    "Thane": 39,
    "Ahmedabad": 38,
    "Delhi": 37,
    "Salem": 35,
    "Jaipur": 34,
    "Raipur": 32,
    "Nagpur": 31,
    "Indore": 30,
    "Varanasi": 30,
    "Kanpur": 26,
    "Thrissur": 26,
    "Ernakulam": 25,
    "Patna": 25,
    "Agra": 24,
    "Madurai": 23,
    "Visakhapatnam": 23,
    "Ghaziabad": 22,
    "Tiruchirappalli": 21,
    "Kanyakumari": 21,
    "Surat": 21,
    "Medchal": 21,
    "Sangli": 20,
    "Mysore": 20,
    "Vijayawada": 19,
    "Jabalpur": 19,
    "Bareilly": 19,
    "Ranchi": 19,
    "Prayagraj": 18,
    "Kanchipuram": 18,
    "Thanjavur": 18,
    "Meerut": 18,
    "Kottayam": 17,
    "Warangal": 17,
    "Ahmednagar": 17,
    "Erode": 16,
    "Kolhapur": 16,
    "Gwalior": 16,
    "Mangalore": 15,
    "Hisar": 15,
    "Ujjain": 15,
    "Ludhiana": 15,
    "North 24 Parganas": 15,
    "Tirunelveli": 14,
    "Dindigul": 14,
    "Aurangabad": 14,
    "Dehradun": 14,
    "Rangareddy": 14,
    "New Delhi": 13,
    "Kollam": 13,
    "Solapur": 13,
    "Moradabad": 13,
    "Kannur": 12,
    "Guwahati": 12,
    "Gorakhpur": 12,
    "Udaipur": 12,
    "Bilaspur": 12,
    "Vadodara": 12,
    "Haridwar": 12,
    "Thiruvananthapuram": 11,
    "Bagalkot": 11,
    "Alappuzha": 11,
    "Malappuram": 11,
    "Amritsar": 11,
    "South 24 Parganas": 11,
    "Khordha": 11,
    "Noida": 10,
    "Faridabad": 10,
    "Udupi": 10,
    "Darjeeling": 10,
    "Sikar": 10,
    "Mumbai City": 10,
    "Trichy": 9,
    "Namakkal": 9,
    "Jhajjar": 9,
    "Thiruvallur": 9,
    "Cuttack": 9,
    "Krishna": 9,
    "Bardhaman": 9,
    "Davanagere": 8,
    "Tirupur": 8,
    "Krishnagiri": 8,
    "West Godavari": 8,
    "Pondicherry": 8,
    "Nadia": 8,
    "Azamgarh": 8,
    "Chittor": 8,
    "Palakkad": 8,
    "Alwar": 8,
    "Dhule": 8,
    "Raigarh": 8,
    "Nashik": 8,
    "Jhunjhunu": 8,
    "Vizianagaram": 7,
    "Dibrugarh": 7,
    "Pathanamthitta": 7,
    "Shimoga": 7,
    "Perambalur": 7,
    "Rewa": 7,
    "Pudukkottai": 7,
    "Dharwad": 7,
    "Kozhikode": 7,
    "Idukki": 7,
    "Greater Noida": 7,
    "Gurgaon": 7,
    "Jodhpur": 7,
    "Valsad": 7,
    "Howrah": 7,
    "East Godavari": 7,
    "Udham Singh Nagar": 7,
    "Gautam Buddha Nagar": 7,
    "Bhilwara": 6,
    "Amravati": 6,
    "Vellore": 6,
    "Sonipat": 6,
    "Karimnagar": 6,
    "Nasik": 6,
    "Nellore": 6,
    "Rajkot": 6,
    "Satara": 6,
    "Saharanpur": 6,
    "Muzaffarpur": 6,
    "Prakasam": 6,
    "Burdwan": 6,
    "Tirupati": 6,
    "Birbhum": 6,
    "Dhanbad": 6,
    "Durg": 6,
    "Murshidabad": 6,
    "Bhavnagar": 6,
    "Chittoor": 6,
    "Tumkur": 6,
    "Navi Mumbai": 5,
    "Aligarh": 5,
    "Karur": 5,
    "Hassan": 5,
    "Jaunpur": 5,
    "Wayanad": 5,
    "Rohtak": 5,
    "Siliguri": 5,
    "Raigad": 5,
    "Jhansi": 5,
    "Yavatmal": 5,
    "Kota": 5,
    "Srikakulam": 5,
    "Bankura": 5,
    "Belgaum": 4,
    "Vijayapur": 4,
    "Karaikudi": 4,
    "Shillong": 4,
    "Virudhunagar": 4,
    "Theni": 4,
    "Trivandrum": 4,
    "Ongole": 4,
    "Faizabad": 4,
    "Gadag": 4,
    "Palghar": 4,
    "Sagar": 4,
    "Hubli": 4,
    "Kadapa": 4,
    "Tiruvannamalai": 4,
    "Haldwani (Nanital)": 4,
    "Jalna": 4,
    "Durgapur": 4,
    "Chandrapur": 4,
    "Jalgaon": 4,
    "Kamrup": 4,
    "Secunderabad": 4,
    "Ratnagiri": 4,
    "Nanded": 4,
    "Hooghly": 4,
    "Kurnool": 4,
    "Darbhanga": 4,
    "Pratapgarh": 4,
    "Ganganagar": 4,
    "West Burdwan": 4,
    "Bhilai": 3,
    "Rajahmundry": 3,
    "Dharmapuri": 3,
    "Kalaburgi": 3,
    "Kannauj": 3,
    "Kolar": 3,
    "Tuticorin": 3,
    "Gulbarga": 3,
    "Shahdol": 3,
    "Khammam": 3,
    "Etawah": 3,
    "Sirsa": 3,
    "Hoshangabad": 3,
    "South Goa": 3,
    "Bahadurgarh": 3,
    "Latur": 3,
    "Panipat": 3,
    "Mathura": 3,
    "Calicut": 3,
    "Akola": 3,
    "Anand": 3,
    "Guna": 3,
    "Anantapur": 3,
    "Begusarai": 3,
    "Bidar": 3,
    "Thoothukudi": 3,
    "Aizawl": 3,
    "Barwani": 3,
    "Dewas": 3,
    "Nagaur": 3,
    "Medinipur": 3,
    "Bellary": 3,
    "Mahasamund": 3,
    "Kamrup Metropolitan": 3,
    "Jalore": 3,
    "Kachchh": 3,
    "Bijnor": 3,
    "Sangareddy": 3,
    "Jhalawar": 3,
    "Chandauli": 3,
    "Puducherry": 3,
    "Purba Medinipur": 3,
    "Narsinghpur": 3,
    "Bokaro": 3,
    "Mumbai Suburban": 3,
    "Sant Kabir Nagar": 3,
    "Jalpaiguri": 3,
    "Ranga Reddy": 3,
    "Ambedkar Nagar": 2,
    "Cuddalore": 2,
    "Kukatpally": 2,
    "Kutch": 2,
    "Kaithal": 2,
    "Chamarajanagar": 2,
    "Satna": 2,
    "Puttur": 2,
    "Katni": 2,
    "Panvel": 2,
    "Suryapet": 2,
    "Kochi": 2,
    "Baraut": 2,
    "Mandya": 2,
    "Panchkula": 2,
    "Karnal": 2,
    "Adoor": 2,
    "Muzaffarnagar": 2,
    "Belagavi": 2,
    "Palwal": 2,
    "Mohali": 2,
    "Rudrapur": 2,
    "Pathankot": 2,
    "Osmanabad": 2,
    "Rewari": 2,
    "Sultanpur": 2,
    "Hardoi": 2,
    "Thodupuzha": 2,
    "Miraj": 2,
    "Ajmer": 2,
    "Ambala": 2,
    "Malda": 2,
    "Bikaner": 2,
    "Dhar": 2,
    "Aluva": 2,
    "Kalyan": 2,
    "Navsari": 2,
    "Chalakudy": 2,
    "Ramanathapuram": 2,
    "Mahbubnagar": 2,
    "Bhubneshwar": 2,
    "Dhamtari": 2,
    "Chittorgarh": 2,
    "Sonbhadra": 2,
    "Burhanpur": 2,
    "Sri Ganganagar": 2,
    "Sundergarh": 2,
    "East Champaran": 2,
    "Betul": 2,
    "Sawai Madhopur": 2,
    "Cherthala": 2,
    "Bhadohi": 2,
    "Navrangpura": 2,
    "Vidisha": 2,
    "Uttar Dinajpur": 2,
    "Bhiwani": 2,
    "Buldhana": 2,
    "Barabanki": 2,
    "Baghpat": 2,
    "Firozabadad": 2,
    "Viluppuram": 2,
    "Dakshina Kannada": 2,
    "Kheda": 2,
    "Parbhani": 2,
    "Nandurbar": 2,
    "Jamshedpur": 2,
    "Kasargod": 2,
    "Mahendragarh": 2,
    "Ambikapur": 2,
    "Hathras": 2,
    "Rajnandgaon": 2,
    "Gonda": 2,
    "Sivaganga": 2,
    "Ballia": 2,
    "Ganjam": 2,
    "Bulandshahr": 2,
    "Allahabad": 2,
    "Gandhinagar": 2,
    "Haveri": 2,
    "West Nimar": 2,
    "Chikmagalur": 2,
    "Basti": 2,
    "Siddipet": 2,
    "Korba": 2,
    "Periakulam": 1,
    "Chettupattu": 1,
    "Ulubari": 1,
    "Hoshangabaad": 1,
    "Tiruvalla": 1,
    "Fatehabad": 1,
    "Ravindra Nagar": 1,
    "Imphal": 1,
    "Devakottai": 1,
    "Tiruvarur": 1,
    "Chikkamagalur": 1,
    "Sitapur": 1,
    "Haveli": 1,
    "Wardha": 1,
    "Tezpur": 1,
    "Jalandhar": 1,
    "Banda": 1,
    "Sidhi": 1,
    "Honavar": 1,
    "Karimganj": 1,
    "Unnao": 1,
    "Yamuna Nagar": 1,
    "Rajam": 1,
    "Belgharia": 1,
    "Nalgonda": 1,
    "Rambagh": 1,
    "Junagadh": 1,
    "Khurda": 1,
    "Nadiad": 1,
    "Fatehpur": 1,
    "Hamirpur": 1,
    "Palamau": 1,
    "Bidhannagar": 1,
    "Sirohi": 1,
    "Rampur": 1,
    "Khurja": 1,
    "Behror": 1,
    "Vilupuram": 1,
    "Ranebennur": 1,
    "Bhilai-Durg": 1,
    "Tumakuru": 1,
    "Maharajganj": 1,
    "Maddur": 1,
    "Mainpuri": 1,
    "Ferozpur City": 1,
    "Raibarelli": 1,
    "Hanmakonda": 1,
    "Dimapur": 1,
    "Aravalli": 1,
    "Agartala": 1,
    "Kathua": 1,
    "Kakinada": 1,
    "Mandla": 1,
    "Ananthapur": 1,
    "Perintalmanna": 1,
    "Mahabubnagar": 1,
    "Chittur": 1,
    "Raisen": 1,
    "Bhubaneswar": 1,
    "Bathinda": 1,
    "Berhampore": 1,
    "Kottakkal": 1,
    "Bodeli": 1,
    "Shajapur": 1,
    "Bahraich": 1,
    "Kumbakkonam": 1,
    "Kunnamkulam": 1,
    "Vile Parle West": 1,
    "Tarn Taran": 1,
    "Bharatpur": 1,
    "Dungarpur": 1,
    "Kamareddy": 1,
    "Baleshwar": 1,
    "Chhatarpur": 1,
    "Kashipur": 1,
    "Seshadripuram": 1,
    "Gir Somnath": 1,
    "Nizamabad": 1,
    "Mehsana": 1,
    "Sindhudurg": 1,
    "Baramati": 1,
    "Nandyal": 1,
    "Kozhencherry": 1,
    "Sonarpur": 1,
    "Ariyalur": 1,
    "Chengannur": 1,
    "Gondia": 1,
    "Purba Bardhaman": 1,
    "Fatehgarh": 1,
    "Gangtok": 1,
    "Hosur": 1,
    "Barmer": 1,
    "Rajsamand": 1,
    "Modasa": 1,
    "Hazaribagh": 1,
    "Hanamkonda": 1,
    "Ranaghat": 1,
    "Asansol": 1,
    "Banaskantha": 1,
    "Sahibganj": 1,
    "West Jaintia Hills": 1,
    "Cooch Behar": 1,
    "Bijapur": 1,
    "Bageshwar": 1,
    "Sonitpur": 1,
    "Pauri Garhwal": 1,
    "Jamnagar": 1,
    "Tikamgarh": 1,
    "Shahid Bhagat Singh Nagar": 1,
    "Dohad": 1,
    "Jajpur": 1,
    "Kurukshetra": 1,
    "Shahdara": 1,
    "Mahisagar": 1,
    "Jorhat": 1,
    "Morena": 1,
    "Siwan": 1,
    "Srinagar": 1,
    "Bongaigaon": 1,
    "Banswara": 1,
    "North West Delhi": 1,
    "Nainital": 1,
    "Goalpara": 1,
    "Hoshiarpur": 1,
    "Budaun": 1,
    "Neemuch": 1,
    "Damoh": 1,
    "North Goa": 1,
    "Madhepura": 1,
    "Harda": 1,
    "South Delhi": 1,
    "South East Delhi": 1,
    "Tonk": 1,
    "Tamaka": 1,
    "Angul": 1,
    "Sehore": 1,
    "Mandsaur": 1,
    "Vikarabad": 1,
    "Beed": 1,
    "Shahjanpur": 1,
    "Vaishali": 1,
    "Puruliya": 1,
    "Pithoragarh": 1,
    "East Singhbhum": 1,
    "Surguja": 1,
    "Panchsheel Nagar District (Hapur)": 1,
    "Bastar": 1,
    "Nalanda": 1,
    "Almora": 1,
    "East Delhi": 1,
    "Ramgarh": 1,
    "Kanpur Dehat (Ramabai Nagar)": 1,
    "South West Delhi": 1,
    "Pilibhit": 1,
    "Nawada": 1,
    "Chhindwara": 1,
    "Balangir": 1,
    "Janjgir Champa": 1,
    "Sivasagar": 1,
    "Badgam": 1,
    "Chamoli": 1,
    "Sivagangai": 1,
    "Kasaragod": 1
  },
  "by_certification_status": {
    "Expired": 1750,
    "Active": 1279
  },
  "by_year": {
    "2015": 10,
    "2024": 610,
    "2022": 296,
    "2017": 98,
    "2023": 582,
    "2025": 547,
    "2018": 188,
    "2016": 80,
    "2021": 269,
    "2020": 169,
    "2019": 180
  },
  "data_quality": {
    "with_accreditation_number": 3029,
    "with_validity_dates": 3029,
    "with_location_info": 3029,
    "active_certifications": 1279,
    "expired_certifications": 1750
  },
  "sample_hospitals": [
    {
      "serial_number": "1",
      "reference_number": "PEH-2014-0004",
      "name": "Kalyani Kidney Care Centre, Erode, Tamil Nadu, India",
      "accreditation_number": "PEH-2015-0001",
      "valid_from": "04 May 2015",
      "valid_upto": "03 May 2017",
      "remarks": "Certification Expired",
      "accreditation_level": "Entry Level",
      "accreditation_category": "NABH Entry Level",
      "country": "India",
      "source": "NABH Entry Level Portal",
      "scraped_date": "2025-09-27T14:29:42.840486",
      "portal_url": "https://portal.nabh.co/frmViewAccreditedEntryLevelHosp.aspx",
      "row_number": 1,
      "city": "Erode",
      "state": "Tamil Nadu",
      "address": "Erode, Tamil Nadu, India",
      "valid_from_parsed": "2015-05-04",
      "valid_upto_parsed": "2017-05-03",
      "certification_status": "Expired"
    },
    {
      "serial_number": "2",
      "reference_number": "PEH-2014-0005",
      "name": "Kauvery Heart City- Unit of Sri Kavery Medical Care (Trichy) Limited, Tiruchirappalli, Tamil Nadu, India",
      "accreditation_number": "PEH-2015-0002",
      "valid_from": "04 May 2015",
      "valid_upto": "03 May 2017",
      "remarks": "Certification Expired",
      "accreditation_level": "Entry Level",
      "accreditation_category": "NABH Entry Level",
      "country": "India",
      "source": "NABH Entry Level Portal",
      "scraped_date": "2025-09-27T14:29:42.841485",
      "portal_url": "https://portal.nabh.co/frmViewAccreditedEntryLevelHosp.aspx",
      "row_number": 2,
      "city": "Tiruchirappalli",
      "state": "Tamil Nadu",
      "address": "Tiruchirappalli, Tamil Nadu, India",
      "valid_from_parsed": "2015-05-04",
      "valid_upto_parsed": "2017-05-03",
      "certification_status": "Expired"
    },
    {
      "serial_number": "3",
      "reference_number": "PEH-2015-0023",
      "name": "Manu Hospital, Coimbatore, Tamil Nadu, India",
      "accreditation_number": "PEH-2015-0003",
      "valid_from": "04 May 2015",
      "valid_upto": "03 May 2017",
      "remarks": "Certification Expired",
      "accreditation_level": "Entry Level",
      "accreditation_category": "NABH Entry Level",
      "country": "India",
      "source": "NABH Entry Level Portal",
      "scraped_date": "2025-09-27T14:29:42.841485",
      "portal_url": "https://portal.nabh.co/frmViewAccreditedEntryLevelHosp.aspx",
      "row_number": 3,
      "city": "Coimbatore",
      "state": "Tamil Nadu",
      "address": "Coimbatore, Tamil Nadu, India",
      "valid_from_parsed": "2015-05-04",
      "valid_upto_parsed": "2017-05-03",
      "certification_status": "Expired"
    },
    {
      "serial_number": "4",
      "reference_number": "H-2010-0401",
      "name": "Jawaharlal Nehru Hospital & Research Centre, Bhilai, Chattisgarh, India",
      "accreditation_number": "PEH-2015-0005",
      "valid_from": "24 Dec 2024",
      "valid_upto": "23 Dec 2026",
      "remarks": "",
      "accreditation_level": "Entry Level",
      "accreditation_category": "NABH Entry Level",
      "country": "India",
      "source": "NABH Entry Level Portal",
      "scraped_date": "2025-09-27T14:29:42.842485",
      "portal_url": "https://portal.nabh.co/frmViewAccreditedEntryLevelHosp.aspx",
      "row_number": 4,
      "city": "Bhilai",
      "state": "Chattisgarh",
      "address": "Bhilai, Chattisgarh, India",
      "valid_from_parsed": "2024-12-24",
      "valid_upto_parsed": "2026-12-23",
      "certification_status": "Active"
    },
    {
      "serial_number": "5",
      "reference_number": "PEH-2015-0049",
      "name": "District Hospital, Kannur, Kerala, India",
      "accreditation_number": "PEH-2015-0006",
      "valid_from": "03 Aug 2015",
      "valid_upto": "02 Aug 2017",
      "remarks": "Certification Expired",
      "accreditation_level": "Entry Level",
      "accreditation_category": "NABH Entry Level",
      "country": "India",
      "source": "NABH Entry Level Portal",
      "scraped_date": "2025-09-27T14:29:42.852388",
      "portal_url": "https://portal.nabh.co/frmViewAccreditedEntryLevelHosp.aspx",
      "row_number": 5,
      "city": "Kannur",
      "state": "Kerala",
      "address": "Kannur, Kerala, India",
      "valid_from_parsed": "2015-08-03",
      "valid_upto_parsed": "2017-08-02",
      "certification_status": "Expired"
    },
    {
      "serial_number": "6",
      "reference_number": "PEH-2015-0048",
      "name": "Kauvery Hospital Tennur Unit of Sri Kavery Medical Care (Trichy) Limited, Trichy, Tamil Nadu, India",
      "accreditation_number": "PEH-2015-0007",
      "valid_from": "30 Jun 2022",
      "valid_upto": "29 Jun 2024",
      "remarks": "",
      "accreditation_level": "Entry Level",
      "accreditation_category": "NABH Entry Level",
      "country": "India",
      "source": "NABH Entry Level Portal",
      "scraped_date": "2025-09-27T14:29:42.852388",
      "portal_url": "https://portal.nabh.co/frmViewAccreditedEntryLevelHosp.aspx",
      "row_number": 6,
      "city": "Trichy",
      "state": "Tamil Nadu",
      "address": "Trichy, Tamil Nadu, India",
      "valid_from_parsed": "2022-06-30",
      "valid_upto_parsed": "2024-06-29",
      "certification_status": "Expired"
    },
    {
      "serial_number": "7",
      "reference_number": "PEH-2015-0037",
      "name": "Tirumala Nursing Home, Vizianagaram, Andhra Pradesh, India",
      "accreditation_number": "PEH-2015-0008",
      "valid_from": "02 Sep 2017",
      "valid_upto": "01 Sep 2019",
      "remarks": "Certification Expired",
      "accreditation_level": "Entry Level",
      "accreditation_category": "NABH Entry Level",
      "country": "India",
      "source": "NABH Entry Level Portal",
      "scraped_date": "2025-09-27T14:29:42.852388",
      "portal_url": "https://portal.nabh.co/frmViewAccreditedEntryLevelHosp.aspx",
      "row_number": 7,
      "city": "Vizianagaram",
      "state": "Andhra Pradesh",
      "address": "Vizianagaram, Andhra Pradesh, India",
      "valid_from_parsed": "2017-09-02",
      "valid_upto_parsed": "2019-09-01",
      "certification_status": "Expired"
    },
    {
      "serial_number": "8",
      "reference_number": "PEH-2015-0038",
      "name": "Kamalakar Hospital, Rajahmundry, Andhra Pradesh, India",
      "accreditation_number": "PEH-2015-0009",
      "valid_from": "02 Sep 2015",
      "valid_upto": "01 Sep 2017",
      "remarks": "Certification Expired",
      "accreditation_level": "Entry Level",
      "accreditation_category": "NABH Entry Level",
      "country": "India",
      "source": "NABH Entry Level Portal",
      "scraped_date": "2025-09-27T14:29:42.852388",
      "portal_url": "https://portal.nabh.co/frmViewAccreditedEntryLevelHosp.aspx",
      "row_number": 8,
      "city": "Rajahmundry",
      "state": "Andhra Pradesh",
      "address": "Rajahmundry, Andhra Pradesh, India",
      "valid_from_parsed": "2015-09-02",
      "valid_upto_parsed": "2017-09-01",
      "certification_status": "Expired"
    },
    {
      "serial_number": "9",
      "reference_number": "PEH-2015-0083",
      "name": "Govt.Hospital, Rasipuram, Namakkal, Tamil Nadu, India",
      "accreditation_number": "PEH-2015-0010",
      "valid_from": "10 Sep 2015",
      "valid_upto": "09 Sep 2017",
      "remarks": "Certification Expired",
      "accreditation_level": "Entry Level",
      "accreditation_category": "NABH Entry Level",
      "country": "India",
      "source": "NABH Entry Level Portal",
      "scraped_date": "2025-09-27T14:29:42.852388",
      "portal_url": "https://portal.nabh.co/frmViewAccreditedEntryLevelHosp.aspx",
      "row_number": 9,
      "city": "Namakkal",
      "state": "Tamil Nadu",
      "address": "Rasipuram, Namakkal, Tamil Nadu, India",
      "valid_from_parsed": "2015-09-10",
      "valid_upto_parsed": "2017-09-09",
      "certification_status": "Expired"
    },
    {
      "serial_number": "10",
      "reference_number": "PEH-2014-0001",
      "name": "Rao Hospital, Coimbatore, Tamil Nadu, India",
      "accreditation_number": "PEH-2015-0011",
      "valid_from": "26 Sep 2015",
      "valid_upto": "25 Sep 2017",
      "remarks": "Certification Expired",
      "accreditation_level": "Entry Level",
      "accreditation_category": "NABH Entry Level",
      "country": "India",
      "source": "NABH Entry Level Portal",
      "scraped_date": "2025-09-27T14:29:42.853395",
      "portal_url": "https://portal.nabh.co/frmViewAccreditedEntryLevelHosp.aspx",
      "row_number": 10,
      "city": "Coimbatore",
      "state": "Tamil Nadu",
      "address": "Coimbatore, Tamil Nadu, India",
      "valid_from_parsed": "2015-09-26",
      "valid_upto_parsed": "2017-09-25",
      "certification_status": "Expired"
    }
  ]
}